{"cameraMode":{"drawMode":0,"name":"Shaded","section":"Shading Mode"},"sceneLighting":true,"audioPlay":false,"sceneViewState":{"showFog":true,"showMaterialUpdate":false,"showSkybox":true,"showFlares":true,"showImageEffects":true,"showParticleSystems":true,"showVisualEffectGraphs":true,"m_FxEnabled":true},"in2DMode":false,"pivot":{"x":-8.5286865234375,"y":-4.373021125793457,"z":-36.80343246459961},"rotation":{"x":0.006084745284169912,"y":0.9514511227607727,"z":-0.30720001459121706,"w":0.01884233020246029},"size":8.30105209350586,"orthographic":false}